application/__init__.py
application/application.py
application/graphers.py
application/printers.py
base/__init__.py
base/builder.py
base/constants.py
base/datadef.py
base/memory.py
base/node.py
base/transformer.py
external/__init__.py
external/external.py
external/file.py
external/image.py
external/web.py
model/__init__.py
model/basic.py
model/financial.py
model/model.py
model/statistical.py
mods/__init__.py
pipe/__init__.py
pipe/builders.py
pipe/col_generation.py
pipe/forecast.py
pipe/pipe.py
pipe/select.py
translator/__init__.py
translator/file.py
translator/pdr.py
translator/quandl.py
translator/translator.py
util/__init__.py
util/level_utils.py
util/plotting_utils.py
util/processing_utils.py
util/transformation_utils.py
util/translation_utils.py
validator/__init__.py
validator/array_val.py
validator/base_val.py
validator/pandas_val.py
validator/presets.py
validator/validator.py
dalio-0.0.1.dist-info/LICENCE.txt
dalio-0.0.1.dist-info/METADATA
dalio-0.0.1.dist-info/WHEEL
dalio-0.0.1.dist-info/top_level.txt
dalio-0.0.1.dist-info/RECORD
