Metadata-Version: 2.1
Name: dalio
Version: 0.0.1
Summary: graphical workflow for financial modeling
Home-page: https://dalio.readthedocs.io/en/latest/
Author: Renato Mateus Zimmermann
Author-email: renatomatz@gmail.com
License: UNKNOWN
Platform: UNKNOWN
Classifier: Development Status :: 2 - Pre-Alpha
Classifier: License :: OSI Approved :: GNU General Public License v3 or later (GPLv3+)
Classifier: Programming Language :: Python :: 3 :: Only
Classifier: Programming Language :: Python :: 3.7
Classifier: Operating System :: OS Independent
